wagtailapi
